{"loggingTools":{},"allContent":[{"type":"folder","folderContents":[{"type":"folder","folderContents":[{"type":"folder","folderContents":[{"type":"folder","folderContents":[{"type":"document","ID":488,"path":"Sample files\\Server\\Documents\\tt\\test\\test\\FL 01 GR_01 Flowdiagram Produktion af saltfisk.pdf"}],"path":"Sample files\\Server\\Documents\\tt\\test\\test"}],"path":"Sample files\\Server\\Documents\\tt\\test"}],"path":"Sample files\\Server\\Documents\\tt"},{"type":"document","ID":489,"path":"Sample files\\Server\\Documents\\PB 01 GR_02 Procesbeskrivelse Produktion af saltfisk.docx"},{"type":"document","ID":490,"path":"Sample files\\Server\\Documents\\RI 01 GR_01 Risikoanalyse Produktion af saltfisk.doc"}],"path":"Sample files/Server/Documents/"}],"archive":[{"type":"folder","folderContents":[{"type":"document","ID":491,"path":"Sample files\\Server\\Archive\\FL 01 GR_01 Flowdiagram Produktion af saltfisk.pdf"},{"type":"document","ID":492,"path":"Sample files\\Server\\Archive\\FL 01 GR_01 Flowdiagram Produktion af saltfisk.vsd"},{"type":"document","ID":493,"path":"Sample files\\Server\\Archive\\shit"}],"path":"Sample files/Server/Archive/"}]}